roblox_test_runner/__init__.py
roblox_test_runner/__main__.py
roblox_test_runner/bundler.py
roblox_test_runner/cli.py
roblox_test_runner/config.py
roblox_test_runner/rojo_resolver.py
roblox_test_runner/runner.py
roblox_test_runner/utils.py
roblox_test_runner/commands/__init__.py
roblox_test_runner/commands/auth.py
roblox_test_runner/commands/config.py
roblox_test_runner/commands/init.py
roblox_test_runner/commands/run.py
roblox_test_runner/vendor/__init__.py
roblox_test_runner/vendor/testez/Context.lua
roblox_test_runner/vendor/testez/Expectation.lua
roblox_test_runner/vendor/testez/ExpectationContext.lua
roblox_test_runner/vendor/testez/LifecycleHooks.lua
roblox_test_runner/vendor/testez/TestBootstrap.lua
roblox_test_runner/vendor/testez/TestEnum.lua
roblox_test_runner/vendor/testez/TestPlan.lua
roblox_test_runner/vendor/testez/TestPlanner.lua
roblox_test_runner/vendor/testez/TestResults.lua
roblox_test_runner/vendor/testez/TestRunner.lua
roblox_test_runner/vendor/testez/TestSession.lua
roblox_test_runner/vendor/testez/init.lua
roblox_test_runner/vendor/testez/Reporters/TeamCityReporter.lua
roblox_test_runner/vendor/testez/Reporters/TextReporter.lua
roblox_test_runner/vendor/testez/Reporters/TextReporterQuiet.lua
roblox_test_runner-0.3.4.dist-info/licenses/LICENSE
roblox_test_runner-0.3.4.dist-info/METADATA
roblox_test_runner-0.3.4.dist-info/WHEEL
roblox_test_runner-0.3.4.dist-info/entry_points.txt
roblox_test_runner-0.3.4.dist-info/top_level.txt
roblox_test_runner-0.3.4.dist-info/RECORD
